ochre/__init__.py
ochre/ansi256.py
ochre/color_pair.py
ochre/colorsys.py
ochre/spaces.py
ochre/web.py
ochre-0.4.0.dist-info/LICENSE
ochre-0.4.0.dist-info/WHEEL
ochre-0.4.0.dist-info/METADATA
ochre-0.4.0.dist-info/RECORD
