Metadata-Version: 2.1
Name: ochre
Version: 0.4.0
Summary: A tiny Python package for working with colors in a pragmatic way
Home-page: https://github.com/getcuia/ochre
License: MIT
Keywords: ansi,color-palettes,colors,cuia,hcl,hex,ochre,rgb,web,zero-dependency
Author: Felipe S. S. Schneider
Author-email: schneider.felipe@posgrad.ufsc.br
Requires-Python: >=3.8,<4.0
Classifier: Development Status :: 4 - Beta
Classifier: Intended Audience :: Developers
Classifier: License :: OSI Approved :: MIT License
Classifier: Programming Language :: Python :: 3
Classifier: Programming Language :: Python :: 3.10
Classifier: Programming Language :: Python :: 3.8
Classifier: Programming Language :: Python :: 3.9
Classifier: Topic :: Multimedia :: Graphics
Classifier: Topic :: Scientific/Engineering :: Visualization
Classifier: Topic :: Software Development :: Libraries :: Python Modules
Project-URL: Repository, https://github.com/getcuia/ochre
